oscar/__init__.py
oscar/checks.py
oscar/config.py
oscar/defaults.py
oscar/apps/__init__.py
oscar/apps/address/__init__.py
oscar/apps/address/abstract_models.py
oscar/apps/address/admin.py
oscar/apps/address/apps.py
oscar/apps/address/forms.py
oscar/apps/address/models.py
oscar/apps/address/migrations/0001_initial.py
oscar/apps/address/migrations/0002_auto_20150927_1547.py
oscar/apps/address/migrations/0003_auto_20150927_1551.py
oscar/apps/address/migrations/0004_auto_20170226_1122.py
oscar/apps/address/migrations/0005_regenerate_user_address_hashes.py
oscar/apps/address/migrations/0006_auto_20181115_1953.py
oscar/apps/address/migrations/__init__.py
oscar/apps/analytics/__init__.py
oscar/apps/analytics/abstract_models.py
oscar/apps/analytics/admin.py
oscar/apps/analytics/apps.py
oscar/apps/analytics/models.py
oscar/apps/analytics/receivers.py
oscar/apps/analytics/reports.py
oscar/apps/analytics/scores.py
oscar/apps/analytics/migrations/0001_initial.py
oscar/apps/analytics/migrations/0002_auto_20140827_1705.py
oscar/apps/analytics/migrations/0003_auto_20200801_0817.py
oscar/apps/analytics/migrations/__init__.py
oscar/apps/basket/__init__.py
oscar/apps/basket/abstract_models.py
oscar/apps/basket/admin.py
oscar/apps/basket/apps.py
oscar/apps/basket/forms.py
oscar/apps/basket/formsets.py
oscar/apps/basket/managers.py
oscar/apps/basket/middleware.py
oscar/apps/basket/models.py
oscar/apps/basket/reports.py
oscar/apps/basket/signals.py
oscar/apps/basket/utils.py
oscar/apps/basket/views.py
oscar/apps/basket/migrations/0001_initial.py
oscar/apps/basket/migrations/0002_auto_20140827_1705.py
oscar/apps/basket/migrations/0003_basket_vouchers.py
oscar/apps/basket/migrations/0004_auto_20141007_2032.py
oscar/apps/basket/migrations/0005_auto_20150604_1450.py
oscar/apps/basket/migrations/0006_auto_20160111_1108.py
oscar/apps/basket/migrations/0007_slugfield_noop.py
oscar/apps/basket/migrations/0008_auto_20181115_1953.py
oscar/apps/basket/migrations/0009_line_date_updated.py
thejoeejoee_django_oscar-3.3a0.dist-info/AUTHORS
thejoeejoee_django_oscar-3.3a0.dist-info/LICENSE
thejoeejoee_django_oscar-3.3a0.dist-info/METADATA
thejoeejoee_django_oscar-3.3a0.dist-info/WHEEL
thejoeejoee_django_oscar-3.3a0.dist-info/top_level.txt
thejoeejoee_django_oscar-3.3a0.dist-info/RECORD
